[{"line":1,"uri":"file:src/test/resources/features/Login.feature","id":"login-functionality","keyword":"Feature","name":"Login Functionality","description":"","elements":[{"start_timestamp":"2026-02-12T03:50:50.368Z","line":10,"id":"login-functionality;verify-login-with-multiple-credential-combinations;;2","type":"scenario","keyword":"Scenario Outline","name":"Verify login with multiple credential combinations","description":"","steps":[{"keyword":"Given ","line":4,"match":{"location":"stepdefinitions.LoginTest.user_is_on_login_page()"},"name":"user is on login page","result":{"duration":2970927000,"status":"passed"}},{"keyword":"When ","line":5,"match":{"location":"stepdefinitions.LoginTest.user_enters_username_and_password(java.lang.String,java.lang.String)","arguments":[{"val":"\"${username}\"","offset":21},{"val":"\"${password}\"","offset":48}]},"name":"user enters username \"${username}\" and password \"${password}\"","result":{"duration":1806587500,"status":"passed"}},{"keyword":"Then ","line":6,"match":{"location":"stepdefinitions.LoginTest.result_should_be_displayed(java.lang.String)","arguments":[{"val":"\"success\"","offset":0}]},"name":"\"success\" should be displayed","result":{"duration":80289800,"status":"passed"}}],"before":[{"match":{"location":"hooks.Hooks.setup()"},"result":{"duration":3555095100,"status":"passed"}}],"after":[{"match":{"location":"hooks.Hooks.tearDown(io.cucumber.java.Scenario)"},"result":{"duration":194698400,"status":"passed"}}]},{"start_timestamp":"2026-02-12T03:50:59.145Z","line":11,"id":"login-functionality;verify-login-with-multiple-credential-combinations;;3","type":"scenario","keyword":"Scenario Outline","name":"Verify login with multiple credential combinations","description":"","steps":[{"keyword":"Given ","line":4,"match":{"location":"stepdefinitions.LoginTest.user_is_on_login_page()"},"name":"user is on login page","result":{"duration":840007700,"status":"passed"}},{"keyword":"When ","line":5,"match":{"location":"stepdefinitions.LoginTest.user_enters_username_and_password(java.lang.String,java.lang.String)","arguments":[{"val":"\"invalidUser\"","offset":21},{"val":"\"${password}\"","offset":48}]},"name":"user enters username \"invalidUser\" and password \"${password}\"","result":{"duration":735626000,"status":"passed"}},{"keyword":"Then ","line":6,"match":{"location":"stepdefinitions.LoginTest.result_should_be_displayed(java.lang.String)","arguments":[{"val":"\"error\"","offset":0}]},"name":"\"error\" should be displayed","result":{"duration":61306900,"status":"passed"}}],"before":[{"match":{"location":"hooks.Hooks.setup()"},"result":{"duration":3644735700,"status":"passed"}}],"after":[{"match":{"location":"hooks.Hooks.tearDown(io.cucumber.java.Scenario)"},"result":{"duration":180159600,"status":"passed"}}]},{"start_timestamp":"2026-02-12T03:51:04.613Z","line":12,"id":"login-functionality;verify-login-with-multiple-credential-combinations;;4","type":"scenario","keyword":"Scenario Outline","name":"Verify login with multiple credential combinations","description":"","steps":[{"keyword":"Given ","line":4,"match":{"location":"stepdefinitions.LoginTest.user_is_on_login_page()"},"name":"user is on login page","result":{"duration":1605687800,"status":"passed"}},{"keyword":"When ","line":5,"match":{"location":"stepdefinitions.LoginTest.user_enters_username_and_password(java.lang.String,java.lang.String)","arguments":[{"val":"\"${username}\"","offset":21},{"val":"\"wrongPass\"","offset":48}]},"name":"user enters username \"${username}\" and password \"wrongPass\"","result":{"duration":825856600,"status":"passed"}},{"keyword":"Then ","line":6,"match":{"location":"stepdefinitions.LoginTest.result_should_be_displayed(java.lang.String)","arguments":[{"val":"\"error\"","offset":0}]},"name":"\"error\" should be displayed","result":{"duration":61137000,"status":"passed"}}],"before":[{"match":{"location":"hooks.Hooks.setup()"},"result":{"duration":3459604400,"status":"passed"}}],"after":[{"match":{"location":"hooks.Hooks.tearDown(io.cucumber.java.Scenario)"},"result":{"duration":186698400,"status":"passed"}}]},{"start_timestamp":"2026-02-12T03:51:10.760Z","line":13,"id":"login-functionality;verify-login-with-multiple-credential-combinations;;5","type":"scenario","keyword":"Scenario Outline","name":"Verify login with multiple credential combinations","description":"","steps":[{"keyword":"Given ","line":4,"match":{"location":"stepdefinitions.LoginTest.user_is_on_login_page()"},"name":"user is on login page","result":{"duration":1329714000,"status":"passed"}},{"keyword":"When ","line":5,"match":{"location":"stepdefinitions.LoginTest.user_enters_username_and_password(java.lang.String,java.lang.String)","arguments":[{"val":"\"invalidUser\"","offset":21},{"val":"\"wrongPass\"","offset":48}]},"name":"user enters username \"invalidUser\" and password \"wrongPass\"","result":{"duration":861581800,"status":"passed"}},{"keyword":"Then ","line":6,"match":{"location":"stepdefinitions.LoginTest.result_should_be_displayed(java.lang.String)","arguments":[{"val":"\"error\"","offset":0}]},"name":"\"error\" should be displayed","result":{"duration":61106800,"status":"passed"}}],"before":[{"match":{"location":"hooks.Hooks.setup()"},"result":{"duration":2983739200,"status":"passed"}}],"after":[{"match":{"location":"hooks.Hooks.tearDown(io.cucumber.java.Scenario)"},"result":{"duration":187952100,"status":"passed"}}]},{"start_timestamp":"2026-02-12T03:51:16.197Z","line":14,"id":"login-functionality;verify-login-with-multiple-credential-combinations;;6","type":"scenario","keyword":"Scenario Outline","name":"Verify login with multiple credential combinations","description":"","steps":[{"keyword":"Given ","line":4,"match":{"location":"stepdefinitions.LoginTest.user_is_on_login_page()"},"name":"user is on login page","result":{"duration":15084158600,"status":"passed"}},{"keyword":"When ","line":5,"match":{"location":"stepdefinitions.LoginTest.user_enters_username_and_password(java.lang.String,java.lang.String)","arguments":[{"val":"\"\"","offset":21},{"val":"\"\"","offset":37}]},"name":"user enters username \"\" and password \"\"","result":{"duration":752945000,"status":"passed"}},{"keyword":"Then ","line":6,"match":{"location":"stepdefinitions.LoginTest.result_should_be_displayed(java.lang.String)","arguments":[{"val":"\"error\"","offset":0}]},"name":"\"error\" should be displayed","result":{"duration":271211200,"status":"passed"}}],"before":[{"match":{"location":"hooks.Hooks.setup()"},"result":{"duration":5877526900,"status":"passed"}}],"after":[{"match":{"location":"hooks.Hooks.tearDown(io.cucumber.java.Scenario)"},"result":{"duration":214165900,"status":"passed"}}]},{"start_timestamp":"2026-02-12T03:51:38.405Z","line":16,"id":"login-functionality;verify-login-page-elements-are-visible","type":"scenario","keyword":"Scenario","name":"Verify login page elements are visible","description":"","steps":[{"keyword":"Given ","line":17,"match":{"location":"stepdefinitions.LoginTest.user_is_on_login_page()"},"name":"user is on login page","result":{"duration":1807256200,"status":"passed"}},{"keyword":"Then ","line":18,"match":{"location":"stepdefinitions.LoginTest.login_page_elements_should_be_visible()"},"name":"login page elements should be visible","result":{"duration":87533700,"status":"passed"}}],"before":[{"match":{"location":"hooks.Hooks.setup()"},"result":{"duration":2886088600,"status":"passed"}}],"after":[{"match":{"location":"hooks.Hooks.tearDown(io.cucumber.java.Scenario)"},"result":{"duration":176165200,"status":"passed"}}]},{"start_timestamp":"2026-02-12T03:51:43.367Z","line":20,"id":"login-functionality;verify-error-message-for-invalid-credentials","type":"scenario","keyword":"Scenario","name":"Verify error message for invalid credentials","description":"","steps":[{"keyword":"Given ","line":21,"match":{"location":"stepdefinitions.LoginTest.user_is_on_login_page()"},"name":"user is on login page","result":{"duration":1055906400,"status":"passed"}},{"keyword":"When ","line":22,"match":{"location":"stepdefinitions.LoginTest.user_enters_username_and_password(java.lang.String,java.lang.String)","arguments":[{"val":"\"wronguser\"","offset":21},{"val":"\"wrongpass\"","offset":46}]},"name":"user enters username \"wronguser\" and password \"wrongpass\"","result":{"duration":1049686300,"status":"passed"}},{"keyword":"Then ","line":23,"match":{"location":"stepdefinitions.LoginTest.result_should_be_displayed(java.lang.String)","arguments":[{"val":"\"error\"","offset":0}]},"name":"\"error\" should be displayed","result":{"duration":75582700,"status":"passed"}}],"before":[{"match":{"location":"hooks.Hooks.setup()"},"result":{"duration":3337400700,"status":"passed"}}],"after":[{"match":{"location":"hooks.Hooks.tearDown(io.cucumber.java.Scenario)"},"result":{"duration":176683600,"status":"passed"}}]}],"tags":[]},{"line":1,"uri":"file:src/test/resources/features/Registration.feature","id":"user-registration","keyword":"Feature","name":"User Registration","description":"","elements":[{"start_timestamp":"2026-02-12T03:51:49.066Z","line":3,"id":"user-registration;navigate-to-registration-page","type":"scenario","keyword":"Scenario","name":"Navigate to registration page","description":"","steps":[{"keyword":"Given ","line":4,"match":{"location":"stepdefinitions.RegistrationTest.the_user_is_on_the_home_page()"},"name":"the user is on the home page","result":{"duration":24645200,"status":"passed"}},{"keyword":"When ","line":5,"match":{"location":"stepdefinitions.RegistrationTest.the_user_clicks_on_the_register_link()"},"name":"the user clicks on the register link","result":{"duration":536461500,"status":"passed"}},{"keyword":"Then ","line":6,"match":{"location":"stepdefinitions.RegistrationTest.the_registration_page_should_be_displayed()"},"name":"the registration page should be displayed","result":{"duration":38203000,"status":"passed"}}],"before":[{"match":{"location":"hooks.Hooks.setup()"},"result":{"duration":3369033800,"status":"passed"}}],"after":[{"match":{"location":"hooks.Hooks.tearDown(io.cucumber.java.Scenario)"},"result":{"duration":170486900,"status":"passed"}}]},{"start_timestamp":"2026-02-12T03:51:53.222Z","line":8,"id":"user-registration;register-a-new-user-with-valid-information","type":"scenario","keyword":"Scenario","name":"Register a new user with valid information","description":"","steps":[{"keyword":"Given ","line":9,"match":{"location":"stepdefinitions.RegistrationTest.the_user_is_on_the_registration_page()"},"name":"the user is on the registration page","result":{"duration":1455621100,"status":"passed"}},{"keyword":"When ","line":10,"match":{"location":"stepdefinitions.RegistrationTest.the_user_enters_valid_registration_details()"},"name":"the user enters valid registration details","result":{"duration":1338151700,"status":"passed"}},{"keyword":"Then ","line":11,"match":{"location":"stepdefinitions.RegistrationTest.a_success_message_should_be_displayed()"},"name":"a success message should be displayed","result":{"duration":257937500,"status":"passed"}}],"before":[{"match":{"location":"hooks.Hooks.setup()"},"result":{"duration":2230108900,"status":"passed"}}],"after":[{"match":{"location":"hooks.Hooks.tearDown(io.cucumber.java.Scenario)"},"result":{"duration":205177800,"status":"passed"}}]},{"start_timestamp":"2026-02-12T03:51:58.720Z","line":13,"id":"user-registration;register-user-with-missing-mandatory-fields","type":"scenario","keyword":"Scenario","name":"Register user with missing mandatory fields","description":"","steps":[{"keyword":"Given ","line":14,"match":{"location":"stepdefinitions.RegistrationTest.the_user_is_on_the_registration_page()"},"name":"the user is on the registration page","result":{"duration":739009500,"status":"passed"}},{"keyword":"When ","line":15,"match":{"location":"stepdefinitions.RegistrationTest.the_user_submits_the_form_without_mandatory_fields()"},"name":"the user submits the form without mandatory fields","result":{"duration":2110744500,"status":"passed"}},{"keyword":"Then ","line":16,"match":{"location":"stepdefinitions.RegistrationTest.validation_error_messages_should_be_displayed()"},"name":"validation error messages should be displayed","result":{"duration":411943400,"status":"passed"}}],"before":[{"match":{"location":"hooks.Hooks.setup()"},"result":{"duration":3337973700,"status":"passed"}}],"after":[{"match":{"location":"hooks.Hooks.tearDown(io.cucumber.java.Scenario)"},"result":{"duration":199634300,"status":"passed"}}]},{"start_timestamp":"2026-02-12T03:52:05.531Z","line":18,"id":"user-registration;verify-registration-page-displays-correctly","type":"scenario","keyword":"Scenario","name":"Verify registration page displays correctly","description":"","steps":[{"keyword":"Given ","line":19,"match":{"location":"stepdefinitions.RegistrationTest.the_user_is_on_the_home_page()"},"name":"the user is on the home page","result":{"duration":1127500,"status":"passed"}},{"keyword":"When ","line":20,"match":{"location":"stepdefinitions.RegistrationTest.the_user_clicks_on_the_register_link()"},"name":"the user clicks on the register link","result":{"duration":736361000,"status":"passed"}},{"keyword":"Then ","line":21,"match":{"location":"stepdefinitions.RegistrationTest.the_registration_page_should_be_displayed()"},"name":"the registration page should be displayed","result":{"duration":40669600,"status":"passed"}}],"before":[{"match":{"location":"hooks.Hooks.setup()"},"result":{"duration":2941455700,"status":"passed"}}],"after":[{"match":{"location":"hooks.Hooks.tearDown(io.cucumber.java.Scenario)"},"result":{"duration":178062400,"status":"passed"}}]}],"tags":[]},{"line":1,"uri":"file:src/test/resources/features/accounts.feature","id":"account-overview","keyword":"Feature","name":"Account Overview","description":"","elements":[{"start_timestamp":"2026-02-12T03:52:09.435Z","line":3,"id":"account-overview;verify-overview-page","type":"scenario","keyword":"Scenario","name":"Verify overview page","description":"","steps":[{"keyword":"Given ","line":4,"match":{"location":"stepdefinitions.CommonSteps.user_is_logged_in()"},"name":"user is logged in","result":{"duration":1963804600,"status":"passed"}},{"keyword":"Then ","line":5,"match":{"location":"stepdefinitions.AccountTest.account_overview_should_display()"},"name":"account overview should display","result":{"duration":45480200,"status":"passed"}}],"before":[{"match":{"location":"hooks.Hooks.setup()"},"result":{"duration":3444793300,"status":"passed"}}],"after":[{"match":{"location":"hooks.Hooks.tearDown(io.cucumber.java.Scenario)"},"result":{"duration":165946700,"status":"passed"}}]},{"start_timestamp":"2026-02-12T03:52:15.060Z","line":7,"id":"account-overview;verify-account-overview-and-balances","type":"scenario","keyword":"Scenario","name":"Verify account overview and balances","description":"","steps":[{"keyword":"Given ","line":8,"match":{"location":"stepdefinitions.CommonSteps.user_is_logged_in()"},"name":"user is logged in","result":{"duration":3173277300,"status":"passed"}},{"keyword":"Then ","line":9,"match":{"location":"stepdefinitions.AccountTest.account_overview_should_display()"},"name":"account overview should display","result":{"duration":45833800,"status":"passed"}},{"keyword":"And ","line":10,"match":{"location":"stepdefinitions.AccountTest.account_balances_should_be_visible()"},"name":"account balances should be visible","result":{"duration":40733900,"status":"passed"}}],"before":[{"match":{"location":"hooks.Hooks.setup()"},"result":{"duration":4520586200,"status":"passed"}}],"after":[{"match":{"location":"hooks.Hooks.tearDown(io.cucumber.java.Scenario)"},"result":{"duration":180547500,"status":"passed"}}]}],"tags":[]},{"line":1,"uri":"file:src/test/resources/features/billpay.feature","id":"bill-pay","keyword":"Feature","name":"Bill Pay","description":"","elements":[{"start_timestamp":"2026-02-12T03:52:23.026Z","line":3,"id":"bill-pay;navigate-to-bill-pay","type":"scenario","keyword":"Scenario","name":"Navigate to bill pay","description":"","steps":[{"keyword":"Given ","line":4,"match":{"location":"stepdefinitions.CommonSteps.user_is_logged_in()"},"name":"user is logged in","result":{"duration":1858915700,"status":"passed"}},{"keyword":"When ","line":5,"match":{"location":"stepdefinitions.BillPayTest.user_opens_bill_pay()"},"name":"user opens bill pay","result":{"duration":695976000,"status":"passed"}},{"keyword":"Then ","line":6,"match":{"location":"stepdefinitions.BillPayTest.bill_pay_page_should_display()"},"name":"bill pay page should display","result":{"duration":38422200,"status":"passed"}}],"before":[{"match":{"location":"hooks.Hooks.setup()"},"result":{"duration":2730936300,"status":"passed"}}],"after":[{"match":{"location":"hooks.Hooks.tearDown(io.cucumber.java.Scenario)"},"result":{"duration":174422700,"status":"passed"}}]},{"start_timestamp":"2026-02-12T03:52:28.533Z","line":9,"id":"bill-pay;valid-bill-payment","type":"scenario","keyword":"Scenario","name":"Valid bill payment","description":"","steps":[{"keyword":"Given ","line":10,"match":{"location":"stepdefinitions.CommonSteps.user_is_logged_in()"},"name":"user is logged in","result":{"duration":1123510200,"status":"passed"}},{"keyword":"When ","line":11,"match":{"location":"stepdefinitions.BillPayTest.user_opens_bill_pay()"},"name":"user opens bill pay","result":{"duration":502269600,"status":"passed"}},{"keyword":"And ","line":12,"match":{"location":"stepdefinitions.BillPayTest.user_pays_bill_with_valid_data()"},"name":"user pays bill with valid data","result":{"duration":872050300,"status":"passed"}},{"keyword":"Then ","line":13,"match":{"location":"stepdefinitions.BillPayTest.bill_payment_confirmation_appears()"},"name":"bill payment confirmation appears","result":{"duration":44920300,"status":"passed"}}],"before":[{"match":{"location":"hooks.Hooks.setup()"},"result":{"duration":2270431400,"status":"passed"}}],"after":[{"match":{"location":"hooks.Hooks.tearDown(io.cucumber.java.Scenario)"},"result":{"duration":215757700,"status":"passed"}}]},{"start_timestamp":"2026-02-12T03:52:33.567Z","line":16,"id":"bill-pay;invalid-bill-payment","type":"scenario","keyword":"Scenario","name":"Invalid bill payment","description":"","steps":[{"keyword":"Given ","line":17,"match":{"location":"stepdefinitions.CommonSteps.user_is_logged_in()"},"name":"user is logged in","result":{"duration":1333894500,"status":"passed"}},{"keyword":"When ","line":18,"match":{"location":"stepdefinitions.BillPayTest.user_opens_bill_pay()"},"name":"user opens bill pay","result":{"duration":607434100,"status":"passed"}},{"keyword":"And ","line":19,"match":{"location":"stepdefinitions.BillPayTest.user_pays_bill_with_invalid_data()"},"name":"user pays bill with invalid data","result":{"duration":180897000,"status":"passed"}},{"keyword":"Then ","line":20,"match":{"location":"stepdefinitions.BillPayTest.error_should_display()"},"name":"error should display","result":{"duration":40900800,"status":"passed"}}],"before":[{"match":{"location":"hooks.Hooks.setup()"},"result":{"duration":3337702300,"status":"passed"}}],"after":[{"match":{"location":"hooks.Hooks.tearDown(io.cucumber.java.Scenario)"},"result":{"duration":179054700,"status":"passed"}}]},{"start_timestamp":"2026-02-12T03:52:39.256Z","line":22,"id":"bill-pay;bill-payment-with-amount-greater-than-balance","type":"scenario","keyword":"Scenario","name":"Bill payment with amount greater than balance","description":"","steps":[{"keyword":"Given ","line":23,"match":{"location":"stepdefinitions.CommonSteps.user_is_logged_in()"},"name":"user is logged in","result":{"duration":1561595000,"status":"passed"}},{"keyword":"When ","line":24,"match":{"location":"stepdefinitions.BillPayTest.user_opens_bill_pay()"},"name":"user opens bill pay","result":{"duration":649087400,"status":"passed"}},{"keyword":"And ","line":25,"match":{"location":"stepdefinitions.BillPayTest.user_pays_bill_with_amount_greater_than_balance()"},"name":"user pays bill with amount greater than balance","result":{"duration":712604200,"status":"passed"}},{"keyword":"Then ","line":26,"match":{"location":"stepdefinitions.BillPayTest.bill_payment_should_fail()"},"name":"bill payment should fail","result":{"duration":566568200,"status":"passed"}}],"before":[{"match":{"location":"hooks.Hooks.setup()"},"result":{"duration":3351058100,"status":"passed"}}],"after":[{"match":{"location":"hooks.Hooks.tearDown(io.cucumber.java.Scenario)"},"result":{"duration":169382700,"status":"passed"}}]}],"tags":[]},{"line":1,"uri":"file:src/test/resources/features/logout.feature","id":"logout","keyword":"Feature","name":"Logout","description":"","elements":[{"start_timestamp":"2026-02-12T03:52:46.271Z","line":3,"id":"logout;verify-logout","type":"scenario","keyword":"Scenario","name":"Verify logout","description":"","steps":[{"keyword":"Given ","line":4,"match":{"location":"stepdefinitions.CommonSteps.user_is_logged_in()"},"name":"user is logged in","result":{"duration":1101035400,"status":"passed"}},{"keyword":"When ","line":5,"match":{"location":"stepdefinitions.LogoutTest.user_clicks_logout()"},"name":"user clicks logout","result":{"duration":709454700,"status":"passed"}},{"keyword":"Then ","line":6,"match":{"location":"stepdefinitions.LogoutTest.session_should_terminate()"},"name":"session should terminate","result":{"duration":37058300,"status":"passed"}}],"before":[{"match":{"location":"hooks.Hooks.setup()"},"result":{"duration":2176953700,"status":"passed"}}],"after":[{"match":{"location":"hooks.Hooks.tearDown(io.cucumber.java.Scenario)"},"result":{"duration":175663600,"status":"passed"}}]},{"start_timestamp":"2026-02-12T03:52:50.477Z","line":8,"id":"logout;verify-session-ends-after-logout","type":"scenario","keyword":"Scenario","name":"Verify session ends after logout","description":"","steps":[{"keyword":"Given ","line":9,"match":{"location":"stepdefinitions.CommonSteps.user_is_logged_in()"},"name":"user is logged in","result":{"duration":1654624000,"status":"passed"}},{"keyword":"When ","line":10,"match":{"location":"stepdefinitions.LogoutTest.user_clicks_logout()"},"name":"user clicks logout","result":{"duration":818801000,"status":"passed"}},{"keyword":"Then ","line":11,"match":{"location":"stepdefinitions.LogoutTest.session_should_terminate()"},"name":"session should terminate","result":{"duration":38724400,"status":"passed"}}],"before":[{"match":{"location":"hooks.Hooks.setup()"},"result":{"duration":3311704200,"status":"passed"}}],"after":[{"match":{"location":"hooks.Hooks.tearDown(io.cucumber.java.Scenario)"},"result":{"duration":177966700,"status":"passed"}}]}],"tags":[]},{"line":1,"uri":"file:src/test/resources/features/transfer.feature","id":"transfer-funds","keyword":"Feature","name":"Transfer Funds","description":"","elements":[{"start_timestamp":"2026-02-12T03:52:56.486Z","line":3,"id":"transfer-funds;navigate-to-transfer-page","type":"scenario","keyword":"Scenario","name":"Navigate to transfer page","description":"","steps":[{"keyword":"Given ","line":4,"match":{"location":"stepdefinitions.CommonSteps.user_is_logged_in()"},"name":"user is logged in","result":{"duration":1499970600,"status":"passed"}},{"keyword":"When ","line":5,"match":{"location":"stepdefinitions.TransferFundsTest.user_opens_transfer_funds()"},"name":"user opens transfer funds","result":{"duration":492604300,"status":"passed"}},{"keyword":"Then ","line":6,"match":{"location":"stepdefinitions.TransferFundsTest.transfer_page_should_display()"},"name":"transfer page should display","result":{"duration":47879600,"status":"passed"}}],"before":[{"match":{"location":"hooks.Hooks.setup()"},"result":{"duration":2808219800,"status":"passed"}}],"after":[{"match":{"location":"hooks.Hooks.tearDown(io.cucumber.java.Scenario)"},"result":{"duration":198266500,"status":"passed"}}]},{"start_timestamp":"2026-02-12T03:53:01.537Z","line":9,"id":"transfer-funds;valid-transfer","type":"scenario","keyword":"Scenario","name":"Valid transfer","description":"","steps":[{"keyword":"Given ","line":10,"match":{"location":"stepdefinitions.CommonSteps.user_is_logged_in()"},"name":"user is logged in","result":{"duration":1594634300,"status":"passed"}},{"keyword":"When ","line":11,"match":{"location":"stepdefinitions.TransferFundsTest.user_opens_transfer_funds()"},"name":"user opens transfer funds","result":{"duration":634209500,"status":"passed"}},{"keyword":"And ","line":12,"match":{"location":"stepdefinitions.TransferFundsTest.user_transfers_valid_amount()"},"name":"user transfers valid amount","result":{"duration":266366400,"status":"passed"}},{"keyword":"Then ","line":13,"match":{"location":"stepdefinitions.TransferFundsTest.transfer_success_message_should_appear()"},"name":"transfer success message should appear","result":{"duration":40217400,"status":"passed"}}],"before":[{"match":{"location":"hooks.Hooks.setup()"},"result":{"duration":3790841800,"status":"passed"}}],"after":[{"match":{"location":"hooks.Hooks.tearDown(io.cucumber.java.Scenario)"},"result":{"duration":150477100,"status":"passed"}}]},{"start_timestamp":"2026-02-12T03:53:08.023Z","line":16,"id":"transfer-funds;invalid-transfer","type":"scenario","keyword":"Scenario","name":"Invalid transfer","description":"","steps":[{"keyword":"Given ","line":17,"match":{"location":"stepdefinitions.CommonSteps.user_is_logged_in()"},"name":"user is logged in","result":{"duration":2023059600,"status":"passed"}},{"keyword":"When ","line":18,"match":{"location":"stepdefinitions.TransferFundsTest.user_opens_transfer_funds()"},"name":"user opens transfer funds","result":{"duration":1222140600,"status":"passed"}},{"keyword":"And ","line":19,"match":{"location":"stepdefinitions.TransferFundsTest.user_transfers_invalid_amount()"},"name":"user transfers invalid amount","result":{"duration":169676900,"status":"passed"}},{"keyword":"Then ","line":20,"match":{"location":"stepdefinitions.TransferFundsTest.error_message_should_displayed()"},"name":"error message should be displayed","result":{"duration":564741400,"status":"passed"}}],"before":[{"match":{"location":"hooks.Hooks.setup()"},"result":{"duration":4170134700,"status":"passed"}}],"after":[{"match":{"location":"hooks.Hooks.tearDown(io.cucumber.java.Scenario)"},"result":{"duration":201453600,"status":"passed"}}]},{"start_timestamp":"2026-02-12T03:53:16.378Z","line":22,"id":"transfer-funds;transfer-amount-greater-than-available-balance","type":"scenario","keyword":"Scenario","name":"Transfer amount greater than available balance","description":"","steps":[{"keyword":"Given ","line":23,"match":{"location":"stepdefinitions.CommonSteps.user_is_logged_in()"},"name":"user is logged in","result":{"duration":2006219400,"status":"passed"}},{"keyword":"When ","line":24,"match":{"location":"stepdefinitions.TransferFundsTest.user_opens_transfer_funds()"},"name":"user opens transfer funds","result":{"duration":538185400,"status":"passed"}},{"keyword":"And ","line":25,"match":{"location":"stepdefinitions.TransferFundsTest.user_transfers_amount_greater_than_balance()"},"name":"user transfers amount greater than balance","result":{"duration":218222800,"status":"passed"}},{"keyword":"Then ","line":26,"match":{"location":"stepdefinitions.TransferFundsTest.transfer_should_fail()"},"name":"transfer should fail","result":{"duration":573896500,"status":"passed"}}],"before":[{"match":{"location":"hooks.Hooks.setup()"},"result":{"duration":2200076100,"status":"passed"}}],"after":[{"match":{"location":"hooks.Hooks.tearDown(io.cucumber.java.Scenario)"},"result":{"duration":185177800,"status":"passed"}}]}],"tags":[]},{"line":1,"uri":"file:src/test/resources/features/update.feature","id":"update-contact-info","keyword":"Feature","name":"Update Contact Info","description":"","elements":[{"start_timestamp":"2026-02-12T03:53:22.106Z","line":3,"id":"update-contact-info;navigate-to-contact-update","type":"scenario","keyword":"Scenario","name":"Navigate to contact update","description":"","steps":[{"keyword":"Given ","line":4,"match":{"location":"stepdefinitions.CommonSteps.user_is_logged_in()"},"name":"user is logged in","result":{"duration":1749902700,"status":"passed"}},{"keyword":"When ","line":5,"match":{"location":"stepdefinitions.UpdateContactTest.user_opens_update_contact()"},"name":"user opens update contact","result":{"duration":464114500,"status":"passed"}},{"keyword":"Then ","line":6,"match":{"location":"stepdefinitions.UpdateContactTest.update_page_should_display()"},"name":"update page should display","result":{"duration":46228800,"status":"passed"}}],"before":[{"match":{"location":"hooks.Hooks.setup()"},"result":{"duration":4070745300,"status":"passed"}}],"after":[{"match":{"location":"hooks.Hooks.tearDown(io.cucumber.java.Scenario)"},"result":{"duration":183302100,"status":"passed"}}]},{"start_timestamp":"2026-02-12T03:53:28.630Z","line":8,"id":"update-contact-info;update-valid-data","type":"scenario","keyword":"Scenario","name":"Update valid data","description":"","steps":[{"keyword":"Given ","line":9,"match":{"location":"stepdefinitions.CommonSteps.user_is_logged_in()"},"name":"user is logged in","result":{"duration":1335107800,"status":"passed"}},{"keyword":"When ","line":10,"match":{"location":"stepdefinitions.UpdateContactTest.user_opens_update_contact()"},"name":"user opens update contact","result":{"duration":980404000,"status":"passed"}},{"keyword":"And ","line":11,"match":{"location":"stepdefinitions.UpdateContactTest.user_updates_valid_contact_info()"},"name":"user updates valid contact info","result":{"duration":265576800,"status":"passed"}},{"keyword":"Then ","line":12,"match":{"location":"stepdefinitions.UpdateContactTest.updated_info_should_be_saved()"},"name":"updated info should be saved","result":{"duration":43661300,"status":"passed"}}],"before":[{"match":{"location":"hooks.Hooks.setup()"},"result":{"duration":17281248200,"status":"passed"}}],"after":[{"match":{"location":"hooks.Hooks.tearDown(io.cucumber.java.Scenario)"},"result":{"duration":194964600,"status":"passed"}}]},{"start_timestamp":"2026-02-12T03:53:48.738Z","line":14,"id":"update-contact-info;update-invalid-data","type":"scenario","keyword":"Scenario","name":"Update invalid data","description":"","steps":[{"keyword":"Given ","line":15,"match":{"location":"stepdefinitions.CommonSteps.user_is_logged_in()"},"name":"user is logged in","result":{"duration":1339575600,"status":"passed"}},{"keyword":"When ","line":16,"match":{"location":"stepdefinitions.UpdateContactTest.user_opens_update_contact()"},"name":"user opens update contact","result":{"duration":573246300,"status":"passed"}},{"keyword":"And ","line":17,"match":{"location":"stepdefinitions.UpdateContactTest.user_enters_invalid_contact_info()"},"name":"user enters invalid contact info","result":{"duration":236590700,"status":"passed"}},{"keyword":"Then ","line":18,"match":{"location":"stepdefinitions.UpdateContactTest.validation_errors_appear()"},"name":"validation errors appear","result":{"duration":44898900,"status":"passed"}}],"before":[{"match":{"location":"hooks.Hooks.setup()"},"result":{"duration":2821233900,"status":"passed"}}],"after":[{"match":{"location":"hooks.Hooks.tearDown(io.cucumber.java.Scenario)"},"result":{"duration":169300200,"status":"passed"}}]},{"start_timestamp":"2026-02-12T03:53:53.927Z","line":20,"id":"update-contact-info;verify-update-page-displays-correctly","type":"scenario","keyword":"Scenario","name":"Verify update page displays correctly","description":"","steps":[{"keyword":"Given ","line":21,"match":{"location":"stepdefinitions.CommonSteps.user_is_logged_in()"},"name":"user is logged in","result":{"duration":391933800,"status":"passed"}},{"keyword":"When ","line":22,"match":{"location":"stepdefinitions.UpdateContactTest.user_opens_update_contact()"},"name":"user opens update contact","result":{"duration":1563177900,"status":"passed"}},{"keyword":"Then ","line":23,"match":{"location":"stepdefinitions.UpdateContactTest.update_page_should_display()"},"name":"update page should display","result":{"duration":67251700,"status":"passed"}}],"before":[{"match":{"location":"hooks.Hooks.setup()"},"result":{"duration":2940842100,"status":"passed"}}],"after":[{"match":{"location":"hooks.Hooks.tearDown(io.cucumber.java.Scenario)"},"result":{"duration":163805500,"status":"passed"}}]}],"tags":[]}]